keyway/__init__.py
keyway/keyway.py
keyway-1.0.4.dist-info/LICENSE
keyway-1.0.4.dist-info/METADATA
keyway-1.0.4.dist-info/WHEEL
keyway-1.0.4.dist-info/top_level.txt
keyway-1.0.4.dist-info/RECORD
