Metadata-Version: 2.1
Name: keyway
Version: 1.0.4
Summary: A solution for persistent environment variables.
Author-email: hardchaos <hardchaos.com@gmail.com>
Project-URL: Homepage, https://github.com/hardchaos/keyway
Project-URL: Bug Tracker, https://github.com/hardchaos/keyway/issues
Classifier: Programming Language :: Python :: 3
Classifier: License :: OSI Approved :: MIT License
Classifier: Operating System :: OS Independent
Requires-Python: >=3.9
License-File: LICENSE
Requires-Dist: cryptography (>39.0.0)
